pystorms/__init__.py
pystorms/environment.py
pystorms/utilities.py
pystorms/config/__init__.py
pystorms/config/alpha.yaml
pystorms/config/beta.yaml
pystorms/config/delta.yaml
pystorms/config/epsilon.yaml
pystorms/config/gamma.yaml
pystorms/config/theta.yaml
pystorms/config/zeta.yaml
pystorms/networks/__init__.py
pystorms/networks/alpha.inp
pystorms/networks/beta.inp
pystorms/networks/delta.inp
pystorms/networks/epsilon.inp
pystorms/networks/gamma.inp
pystorms/networks/theta.inp
pystorms/networks/zeta.inp
pystorms/scenarios/__init__.py
pystorms/scenarios/alpha.py
pystorms/scenarios/beta.py
pystorms/scenarios/delta.py
pystorms/scenarios/epsilon.py
pystorms/scenarios/gamma.py
pystorms/scenarios/scenario.py
pystorms/scenarios/theta.py
pystorms/scenarios/zeta.py
pystorms-1.0.0.dist-info/LICENSE
pystorms-1.0.0.dist-info/METADATA
pystorms-1.0.0.dist-info/WHEEL
pystorms-1.0.0.dist-info/top_level.txt
pystorms-1.0.0.dist-info/RECORD
