Metadata-Version: 2.1
Name: pystorms
Version: 1.0.0
Summary: Simulation sandbox for stormwater control algorithms
Home-page: https://github.com/kLabUM/pystorms
Author: Abhiram Mullapudi, Sara C. Troutman, Sara Rimer, Branko Kerkez
Author-email: abhiramm@umich.edu, stroutm@umich.edu
License: UNKNOWN
Platform: UNKNOWN
Classifier: Programming Language :: Python :: 3
Classifier: License :: OSI Approved :: GNU Lesser General Public License v3 (LGPLv3)
Classifier: Operating System :: OS Independent
License-File: LICENSE
Requires-Dist: numpy (>=1.18.4)
Requires-Dist: pyswmm (>=1.0.1)
Requires-Dist: pyyaml (>=5.3)
